llmbot_plugin_sticker/__init__.py
llmbot_plugin_sticker/event.py
llmbot_plugin_sticker/sticker.zip
llmbot_plugin_sticker-0.1.7.dist-info/LICENSE
llmbot_plugin_sticker-0.1.7.dist-info/METADATA
llmbot_plugin_sticker-0.1.7.dist-info/WHEEL
llmbot_plugin_sticker-0.1.7.dist-info/entry_points.txt
llmbot_plugin_sticker-0.1.7.dist-info/RECORD
