Metadata-Version: 2.1
Name: llmbot_plugin_sticker
Version: 0.1.7
Summary: Openaibot Bot Plugin: Sticker,for sending sticker in chat
License: MIT
Author: llmkira
Author-email: me@dianas.cyou
Requires-Python: >=3.8,<4.0
Classifier: License :: OSI Approved :: MIT License
Classifier: Programming Language :: Python :: 3
Classifier: Programming Language :: Python :: 3.8
Classifier: Programming Language :: Python :: 3.9
Classifier: Programming Language :: Python :: 3.10
Classifier: Programming Language :: Python :: 3.11
Requires-Dist: emoji (>=2.8.0,<3.0.0)
